ovos_hivemind_solver/__init__.py
ovos_hivemind_solver/version.py
ovos_solver_hivemind_plugin-0.0.3.dist-info/METADATA
ovos_solver_hivemind_plugin-0.0.3.dist-info/WHEEL
ovos_solver_hivemind_plugin-0.0.3.dist-info/entry_points.txt
ovos_solver_hivemind_plugin-0.0.3.dist-info/top_level.txt
ovos_solver_hivemind_plugin-0.0.3.dist-info/zip-safe
ovos_solver_hivemind_plugin-0.0.3.dist-info/RECORD
