Metadata-Version: 2.1
Name: ovos-solver-hivemind-plugin
Version: 0.0.3
Summary: A question solver plugin for OVOS
Home-page: https://github.com/JarbasHiveMind/ovos-solver-hivemind-plugin
Author: jarbasai
Author-email: jarbasai@mailfence.com
License: MIT
Keywords: OVOS openvoiceos plugin utterance fallback query
Requires-Dist: ovos-plugin-manager
Requires-Dist: ovos-translate-server-plugin
Requires-Dist: hivemind-bus-client>=0.0.4a21
